pyx2pxd/__init__.py
pyx2pxd/cli.py
pyx2pxd/pyx2pxd.py
pyx2pxd-0.1.4.dist-info/LICENSE.txt
pyx2pxd-0.1.4.dist-info/METADATA
pyx2pxd-0.1.4.dist-info/WHEEL
pyx2pxd-0.1.4.dist-info/entry_points.txt
pyx2pxd-0.1.4.dist-info/top_level.txt
pyx2pxd-0.1.4.dist-info/RECORD
