Metadata-Version: 2.1
Name: pyx2pxd
Version: 0.1.4
Summary: Auto generate pxd files from pyx by extracting function and class signatures
Author-email: Ricardo Henriques <ricardo.jv.henriques@gmail.com>, Bruno Saraiva <bruno.msaraiva2@gmail.com>
Maintainer-email: Bruno Saraiva <bruno.msaraiva2@gmail.com>
License: GNU GENERAL PUBLIC LICENSE
Project-URL: repository, https://github.com/HenriquesLab/pyx2pxd
Project-URL: bug_tracker, https://github.com/HenriquesLab/pyx2pxd/issues
Keywords: Cython,pyx,pxd
Classifier: Programming Language :: Python :: 3
Classifier: License :: OSI Approved :: MIT License
Classifier: Operating System :: OS Independent
Requires-Python: >=3.9
License-File: LICENSE.txt
Requires-Dist: cython (>=0.29.0)
Provides-Extra: test
Requires-Dist: pytest (>=7.1) ; extra == 'test'
Requires-Dist: pytest-cov (>=4.0.0) ; extra == 'test'
Requires-Dist: pytest-emoji (>=0.2.0) ; extra == 'test'
Requires-Dist: pytest-icdiff (>=0.6) ; extra == 'test'
Requires-Dist: pytest-clarity (>=1.0.1) ; extra == 'test'
Requires-Dist: pytest-timeout (>=2.1.0) ; extra == 'test'
Requires-Dist: pytest-sugar (>=0.9.6) ; extra == 'test'
Requires-Dist: pytest-cython (>=0.2.0) ; extra == 'test'
